README.md
setup.py
compendium/__init__.py
compendium/__main__.py
compendium/action.py
compendium/compendium.py
compendium/encryption.py
compendium/util.py
compendium/command/__init__.py
compendium/command/check.py
compendium/command/command.py
compendium/command/document.py
compendium/command/encrypt.py
compendium/command/init.py
compendium/initsegment/__init__.py
compendium/initsegment/checksegment.py
compendium/initsegment/folderstructure.py
compendium/initsegment/github.py
compendium/initsegment/pyenv.py
compendium/initsegment/segment.py
compendium_dodo.egg-info/PKG-INFO
compendium_dodo.egg-info/SOURCES.txt
compendium_dodo.egg-info/dependency_links.txt
compendium_dodo.egg-info/entry_points.txt
compendium_dodo.egg-info/requires.txt
compendium_dodo.egg-info/top_level.txt